google_analytics_django/__init__.py
google_analytics_django/admin.py
google_analytics_django/apps.py
google_analytics_django/conf.py
google_analytics_django/middleware.py
google_analytics_django/utils.py
google_analytics_django/templates/google_analytics_django/analytics_gtag.html
google_analytics_django/templatetags/__init__.py
google_analytics_django/templatetags/google_analytics_tags.py
google_analytics_django/templatetags/__pycache__/__init__.cpython-312.pyc
google_analytics_django/templatetags/__pycache__/google_analytics_tags.cpython-312.pyc
google_analytics_django-0.1.4.dist-info/LICENSE
google_analytics_django-0.1.4.dist-info/METADATA
google_analytics_django-0.1.4.dist-info/WHEEL
google_analytics_django-0.1.4.dist-info/top_level.txt
google_analytics_django-0.1.4.dist-info/RECORD
