Metadata-Version: 2.1
Name: google-analytics-django
Version: 0.1.4
Summary: A Django package to integrate Google Analytics seamlessly.
Author-email: Adivhaho Mavhungu <adivhahomavhungu@outlook.com>
Maintainer-email: Adivhaho Mavhungu <adivhahomavhungu@outlook.com>
License: MIT
Project-URL: Source, https://github.com/mavhungutrezzy/google_analytics_django
Project-URL: Bug Tracker, https://github.com/mavhungutrezzy/google_analytics_django/issues
Requires-Python: >=3.10
License-File: LICENSE
Requires-Dist: django<6.0,>=5.0
Provides-Extra: dev
Requires-Dist: coverage>=7.6.3; extra == "dev"
Requires-Dist: djlint>=1.35.2; extra == "dev"
Requires-Dist: pre-commit>=4.0.1; extra == "dev"
Requires-Dist: ruff>=0.6.9; extra == "dev"
Requires-Dist: setuptools>=75.2.0; extra == "dev"
